{
    "name": "monkflavor",
    "title": "Monk Flavor",
    "description": "Roll fun sounding monk attacks!",
    "version": "0.0.1",
    "author": "Leonard Robinson",
    "systems" : ["dnd5e"],
    "packs": [
        {
            "name": "monkFlavor",
            "label": "Monk Flavor",
            "path": "db/monkFlavor.db",
            "module": "monk-flavor",
            "entity": "RollTable"
        }
    ],
    "esmodules": [
        "./src/monkFlavor.js",
        "./config/config.js"
    ],
    "url": "https://github.com/gitlcr2131/monk-flavor-5e",
    "manifest": "https://raw.githubusercontent.com/gitlcr2131/monk-flavor-5e/master/module.json",
    "download": "https://github.com/gitlcr2131/monk-flavor-5e/archive/master.zip",
    "minimumCoreVersion": "0.4.4"
}